<?xml version="1.0" encoding="UTF-8"?>
<billStatus>
  <bill>
    <relatedBills>
      <item>
        <congress>113</congress>
        <latestTitle>Energy Freedom and Economic Prosperity Act</latestTitle>
        <type>HR</type>
        <relationshipDetails>
          <item>
            <identifiedBy>CRS</identifiedBy>
            <type>Related bill</type>
          </item>
        </relationshipDetails>
        <number>259</number>
        <latestAction>
          <actionDate>2013-01-15</actionDate>
          <text>Referred to the House Committee on Ways and Means.</text>
        </latestAction>
      </item>
      <item>
        <congress>113</congress>
        <latestTitle>EXPAND Act</latestTitle>
        <type>HR</type>
        <relationshipDetails>
          <item>
            <identifiedBy>CRS</identifiedBy>
            <type>Related bill</type>
          </item>
        </relationshipDetails>
        <number>3895</number>
        <latestAction>
          <actionDate>2014-06-20</actionDate>
          <text>Referred to the Subcommittee on Readiness.</text>
        </latestAction>
      </item>
      <item>
        <congress>113</congress>
        <latestTitle>Energy Freedom and Economic Prosperity Act of 2014</latestTitle>
        <type>S</type>
        <relationshipDetails>
          <item>
            <identifiedBy>CRS</identifiedBy>
            <type>Related bill</type>
          </item>
        </relationshipDetails>
        <number>2279</number>
        <latestAction>
          <actionDate>2014-05-01</actionDate>
          <text>Read twice and referred to the Committee on Finance.</text>
        </latestAction>
      </item>
    </relatedBills>
    <sponsors>
      <item>
        <fullName>Rep. Pompeo, Mike [R-KS-4]</fullName>
        <bioguideId>P000602</bioguideId>
        <lastName>Pompeo</lastName>
        <middleName />
        <party>R</party>
        <identifiers>
          <lisID>2022</lisID>
          <bioguideId>P000602</bioguideId>
          <gpoId>7952</gpoId>
        </identifiers>
        <firstName>Mike</firstName>
        <state>KS</state>
        <district>4</district>
        <byRequestType />
      </item>
    </sponsors>
    <subjects>
      <billSubjects>
        <legislativeSubjects>
          <item>
            <name>Air quality</name>
          </item>
          <item>
            <name>Alternative and renewable resources</name>
          </item>
          <item>
            <name>Climate change and greenhouse gases</name>
          </item>
          <item>
            <name>Coal</name>
          </item>
          <item>
            <name>Corporate finance and management</name>
          </item>
          <item>
            <name>Electric power generation and transmission</name>
          </item>
          <item>
            <name>Hybrid, electric, and advanced technology vehicles</name>
          </item>
          <item>
            <name>Income tax credits</name>
          </item>
          <item>
            <name>Income tax rates</name>
          </item>
          <item>
            <name>Motor fuels</name>
          </item>
          <item>
            <name>Nuclear power</name>
          </item>
          <item>
            <name>Oil and gas</name>
          </item>
          <item>
            <name>Sales and excise taxes</name>
          </item>
        </legislativeSubjects>
        <policyArea>
          <name>Taxation</name>
        </policyArea>
      </billSubjects>
    </subjects>
    <calendarNumbers />
    <committeeReports />
    <title>New Fair Deal Busting America's Rigid Outdated &amp; Needless Subsidies Act of 2013</title>
    <amendments />
    <recordedVotes />
    <latestAction>
      <text>Referred to the House Committee on Ways and Means.</text>
      <actionDate>2013-04-15</actionDate>
      <links />
    </latestAction>
    <laws />
    <constitutionalAuthorityStatementText><![CDATA[<pre>By Mr. POMPEO:H.R. 1569.Congress has the power to enact this legislation pursuantto the following:Article I, Section 8, Clause 3[[Page H2027]][Page H2026]</pre>]]></constitutionalAuthorityStatementText>
    <introducedDate>2013-04-15</introducedDate>
    <createDate>2013-04-16T07:02:07Z</createDate>
    <cboCostEstimates />
    <billType>HR</billType>
    <titles>
      <item>
        <chamberCode />
        <title>New Fair Deal Busting America's Rigid Outdated &amp; Needless Subsidies Act of 2013</title>
        <titleType>Short Titles as Introduced</titleType>
        <parentTitleType />
        <chamberName />
      </item>
      <item>
        <chamberCode />
        <title>To amend the Internal Revenue Code of 1986 to terminate certain energy tax subsidies and lower the corporate income tax rate.</title>
        <titleType>Official Title as Introduced</titleType>
        <parentTitleType />
        <chamberName />
      </item>
      <item>
        <chamberCode />
        <title>New Fair Deal Busting America's Rigid Outdated &amp; Needless Subsidies Act of 2013</title>
        <titleType>Display Title</titleType>
        <parentTitleType />
        <chamberName />
      </item>
    </titles>
    <summaries>
      <billSummaries>
        <item>
          <actionDate>2013-04-15</actionDate>
          <name>Introduced in House</name>
          <actionDesc>Introduced in House</actionDesc>
          <text><![CDATA[<p>New Fair Deal Busting America's Rigid Outdated &amp; Needless Subsidies Act of 2013 - Amends the Internal Revenue Code to repeal: (1) the excise tax credits for alcohol fuel, biodiesel, and alternative fuel mixtures; (2) the tax credits for the purchase of alternative motor vehicles and new qualified plug-in electric drive motor vehicles; (3) the alternative fuel vehicle refueling property tax credit; (4) the income tax credits for alcohol, biodiesel, and renewable diesel used as fuel; (5) the enhanced oil recovery tax credit and the tax credit for producing oil and gas from marginal wells; (6) the tax credits for producing electricity from renewable resources and from advanced nuclear power facilities; (7) the tax credit for carbon dioxide sequestration; (8) the energy tax credit; and (9) the tax credits for investment in qualifying advanced coal projects and qualifying gasification projects. </p> <p>Directs the Secretary of the Treasury to prescribe a flat income tax rate for corporations, in lieu of the existing marginal tax rates, based upon the overall revenue savings from the repeal of energy tax expenditures by this Act. </p>]]></text>
          <versionCode>00</versionCode>
          <updateDate>2013-04-15T04:00:00Z</updateDate>
          <lastSummaryUpdateDate>2013-04-30T19:29:03Z</lastSummaryUpdateDate>
        </item>
      </billSummaries>
    </summaries>
    <cosponsors>
      <item>
        <isOriginalCosponsor>True</isOriginalCosponsor>
        <sponsorshipWithdrawnDate />
        <lastName>Amash</lastName>
        <bioguideId>A000367</bioguideId>
        <middleName />
        <district>3</district>
        <identifiers>
          <bioguideId>A000367</bioguideId>
          <gpoId>7988</gpoId>
          <lisID>2029</lisID>
        </identifiers>
        <state>MI</state>
        <sponsorshipDate>2013-04-15</sponsorshipDate>
        <firstName>Justin</firstName>
        <fullName>Rep. Amash, Justin [R-MI-3]</fullName>
        <party>R</party>
      </item>
      <item>
        <isOriginalCosponsor>True</isOriginalCosponsor>
        <sponsorshipWithdrawnDate />
        <lastName>McClintock</lastName>
        <bioguideId>M001177</bioguideId>
        <middleName />
        <district>4</district>
        <identifiers>
          <bioguideId>M001177</bioguideId>
          <lisID>1908</lisID>
          <gpoId>7809</gpoId>
        </identifiers>
        <state>CA</state>
        <sponsorshipDate>2013-04-15</sponsorshipDate>
        <firstName>Tom</firstName>
        <fullName>Rep. McClintock, Tom [R-CA-4]</fullName>
        <party>R</party>
      </item>
      <item>
        <isOriginalCosponsor>True</isOriginalCosponsor>
        <sponsorshipWithdrawnDate />
        <lastName>Mulvaney</lastName>
        <bioguideId>M001182</bioguideId>
        <middleName />
        <district>5</district>
        <identifiers>
          <bioguideId>M001182</bioguideId>
          <gpoId>8145</gpoId>
          <lisID>2059</lisID>
        </identifiers>
        <state>SC</state>
        <sponsorshipDate>2013-04-15</sponsorshipDate>
        <firstName>Mick</firstName>
        <fullName>Rep. Mulvaney, Mick [R-SC-5]</fullName>
        <party>R</party>
      </item>
      <item>
        <isOriginalCosponsor>True</isOriginalCosponsor>
        <sponsorshipWithdrawnDate />
        <lastName>Ribble</lastName>
        <bioguideId>R000587</bioguideId>
        <middleName>J.</middleName>
        <district>8</district>
        <identifiers>
          <lisID>2073</lisID>
          <bioguideId>R000587</bioguideId>
          <gpoId>8221</gpoId>
        </identifiers>
        <state>WI</state>
        <sponsorshipDate>2013-04-15</sponsorshipDate>
        <firstName>Reid</firstName>
        <fullName>Rep. Ribble, Reid J. [R-WI-8]</fullName>
        <party>R</party>
      </item>
      <item>
        <isOriginalCosponsor>True</isOriginalCosponsor>
        <sponsorshipWithdrawnDate />
        <lastName>Duncan</lastName>
        <bioguideId>D000615</bioguideId>
        <middleName />
        <district>3</district>
        <identifiers>
          <lisID>2057</lisID>
          <bioguideId>D000615</bioguideId>
          <gpoId>8143</gpoId>
        </identifiers>
        <state>SC</state>
        <sponsorshipDate>2013-04-15</sponsorshipDate>
        <firstName>Jeff</firstName>
        <fullName>Rep. Duncan, Jeff [R-SC-3]</fullName>
        <party>R</party>
      </item>
      <item>
        <isOriginalCosponsor>True</isOriginalCosponsor>
        <sponsorshipWithdrawnDate />
        <lastName>Lamborn</lastName>
        <bioguideId>L000564</bioguideId>
        <middleName />
        <district>5</district>
        <identifiers>
          <bioguideId>L000564</bioguideId>
          <lisID>1834</lisID>
          <gpoId>7863</gpoId>
        </identifiers>
        <state>CO</state>
        <sponsorshipDate>2013-04-15</sponsorshipDate>
        <firstName>Doug</firstName>
        <fullName>Rep. Lamborn, Doug [R-CO-5]</fullName>
        <party>R</party>
      </item>
      <item>
        <isOriginalCosponsor>True</isOriginalCosponsor>
        <sponsorshipWithdrawnDate />
        <lastName>Jordan</lastName>
        <bioguideId>J000289</bioguideId>
        <middleName />
        <district>4</district>
        <identifiers>
          <bioguideId>J000289</bioguideId>
          <lisID>1868</lisID>
          <gpoId>8094</gpoId>
        </identifiers>
        <state>OH</state>
        <sponsorshipDate>2013-04-15</sponsorshipDate>
        <firstName>Jim</firstName>
        <fullName>Rep. Jordan, Jim [R-OH-4]</fullName>
        <party>R</party>
      </item>
      <item>
        <isOriginalCosponsor>True</isOriginalCosponsor>
        <sponsorshipWithdrawnDate />
        <lastName>Meadows</lastName>
        <bioguideId>M001187</bioguideId>
        <middleName />
        <district>11</district>
        <identifiers>
          <gpoId />
          <lisID>2142</lisID>
          <bioguideId>M001187</bioguideId>
        </identifiers>
        <state>NC</state>
        <sponsorshipDate>2013-04-15</sponsorshipDate>
        <firstName>Mark</firstName>
        <fullName>Rep. Meadows, Mark [R-NC-11]</fullName>
        <party>R</party>
      </item>
      <item>
        <isOriginalCosponsor>True</isOriginalCosponsor>
        <sponsorshipWithdrawnDate />
        <lastName>Price</lastName>
        <bioguideId>P000591</bioguideId>
        <middleName />
        <district>6</district>
        <identifiers>
          <lisID>1778</lisID>
          <gpoId>7903</gpoId>
          <bioguideId>P000591</bioguideId>
        </identifiers>
        <state>GA</state>
        <sponsorshipDate>2013-04-15</sponsorshipDate>
        <firstName>Tom</firstName>
        <fullName>Rep. Price, Tom [R-GA-6]</fullName>
        <party>R</party>
      </item>
    </cosponsors>
    <actions>
      <actionTypeCounts>
        <introducedInTheHouse>1</introducedInTheHouse>
        <billReferrals>1</billReferrals>
        <introducedInHouse>1</introducedInHouse>
      </actionTypeCounts>
      <item>
        <actionDate>2013-04-15</actionDate>
        <links />
        <type>IntroReferral</type>
        <sourceSystem>
          <code>2</code>
          <name>House floor actions</name>
        </sourceSystem>
        <actionCode>H11100</actionCode>
        <committee>
          <systemCode>hswm00</systemCode>
          <name>Ways and Means Committee</name>
        </committee>
        <text>Referred to the House Committee on Ways and Means.</text>
      </item>
      <item>
        <actionDate>2013-04-15</actionDate>
        <links />
        <type>IntroReferral</type>
        <sourceSystem>
          <code>9</code>
          <name>Library of Congress</name>
        </sourceSystem>
        <actionCode>Intro-H</actionCode>
        <committee />
        <text>Introduced in House</text>
      </item>
      <item>
        <actionDate>2013-04-15</actionDate>
        <links />
        <type>IntroReferral</type>
        <sourceSystem>
          <code>9</code>
          <name>Library of Congress</name>
        </sourceSystem>
        <actionCode>1000</actionCode>
        <committee />
        <text>Introduced in House</text>
      </item>
      <actionByCounts>
        <houseOfRepresentatives>3</houseOfRepresentatives>
      </actionByCounts>
    </actions>
    <billNumber>1569</billNumber>
    <originChamber>House</originChamber>
    <congress>113</congress>
    <notes />
    <updateDate>2016-10-25T16:02:12Z</updateDate>
    <committees>
      <billCommittees>
        <item>
          <name>Ways and Means Committee</name>
          <chamber>House</chamber>
          <activities>
            <item>
              <name>Referred to</name>
              <date>2013-04-15T16:02:30Z</date>
            </item>
          </activities>
          <systemCode>hswm00</systemCode>
          <type>Standing</type>
          <subcommittees />
        </item>
      </billCommittees>
    </committees>
    <policyArea>
      <name>Taxation</name>
    </policyArea>
  </bill>
  <dublinCore xmlns:dc="http://purl.org/dc/elements/1.1/">
    <dc:format>text/xml</dc:format>
    <dc:language>EN</dc:language>
    <dc:rights>Pursuant to Title 17 Section 105 of the United States Code, this file is not subject to copyright protection and is in the public domain.</dc:rights>
    <dc:contributor>Congressional Research Service, Library of Congress</dc:contributor>
    <dc:description>This file contains bill summaries and statuses for federal legislation. A bill summary describes the most significant provisions of a piece of legislation and details the effects the legislative text may have on current law and federal programs. Bill summaries are authored by the Congressional Research Service (CRS) of the Library of Congress. As stated in Public Law 91-510 (2 USC 166 (d)(6)), one of the duties of CRS is "to prepare summaries and digests of bills and resolutions of a public general nature introduced in the Senate or House of Representatives". For more information, refer to the User Guide that accompanies this file.</dc:description>
  </dublinCore>
</billStatus>

