<?xml version="1.0" encoding="UTF-8"?>
<billStatus>
  <bill>
    <introducedDate>2015-03-12</introducedDate>
    <calendarNumbers />
    <updateDate>2017-10-27T18:08:36Z</updateDate>
    <cosponsors>
      <item>
        <bioguideId>W000817</bioguideId>
        <party>D</party>
        <fullName>Sen. Warren, Elizabeth [D-MA]</fullName>
        <firstName>Elizabeth</firstName>
        <middleName>A.</middleName>
        <lastName>Warren</lastName>
        <sponsorshipWithdrawnDate />
        <sponsorshipDate>2015-03-12</sponsorshipDate>
        <identifiers>
          <lisID>2182</lisID>
          <bioguideId>W000817</bioguideId>
          <gpoId />
        </identifiers>
        <isOriginalCosponsor>True</isOriginalCosponsor>
        <state>MA</state>
      </item>
      <item>
        <bioguideId>R000122</bioguideId>
        <party>D</party>
        <fullName>Sen. Reed, Jack [D-RI]</fullName>
        <firstName>JOHN</firstName>
        <middleName>F.</middleName>
        <lastName>REED</lastName>
        <sponsorshipWithdrawnDate />
        <sponsorshipDate>2015-03-12</sponsorshipDate>
        <identifiers>
          <bioguideId>R000122</bioguideId>
          <gpoId>8272</gpoId>
          <lisID>949</lisID>
        </identifiers>
        <isOriginalCosponsor>True</isOriginalCosponsor>
        <state>RI</state>
      </item>
      <item>
        <bioguideId>F000457</bioguideId>
        <party>D</party>
        <fullName>Sen. Franken, Al [D-MN]</fullName>
        <firstName>Al</firstName>
        <middleName />
        <lastName>Franken</lastName>
        <sponsorshipWithdrawnDate />
        <sponsorshipDate>2015-03-12</sponsorshipDate>
        <identifiers>
          <bioguideId>F000457</bioguideId>
          <gpoId>8339</gpoId>
          <lisID>1969</lisID>
        </identifiers>
        <isOriginalCosponsor>True</isOriginalCosponsor>
        <state>MN</state>
      </item>
      <item>
        <bioguideId>S000770</bioguideId>
        <party>D</party>
        <fullName>Sen. Stabenow, Debbie [D-MI]</fullName>
        <firstName>DEBORAH</firstName>
        <middleName>ANN</middleName>
        <lastName>STABENOW</lastName>
        <sponsorshipWithdrawnDate />
        <sponsorshipDate>2015-03-12</sponsorshipDate>
        <identifiers>
          <bioguideId>S000770</bioguideId>
          <gpoId>8261</gpoId>
          <lisID>1531</lisID>
        </identifiers>
        <isOriginalCosponsor>True</isOriginalCosponsor>
        <state>MI</state>
      </item>
      <item>
        <bioguideId>W000802</bioguideId>
        <party>D</party>
        <fullName>Sen. Whitehouse, Sheldon [D-RI]</fullName>
        <firstName>Sheldon</firstName>
        <middleName />
        <lastName>Whitehouse</lastName>
        <sponsorshipWithdrawnDate />
        <sponsorshipDate>2015-03-12</sponsorshipDate>
        <identifiers>
          <bioguideId>W000802</bioguideId>
          <gpoId>8264</gpoId>
          <lisID>1823</lisID>
        </identifiers>
        <isOriginalCosponsor>True</isOriginalCosponsor>
        <state>RI</state>
      </item>
      <item>
        <bioguideId>M000639</bioguideId>
        <party>D</party>
        <fullName>Sen. Menendez, Robert [D-NJ]</fullName>
        <firstName>ROBERT</firstName>
        <middleName />
        <lastName>MENENDEZ</lastName>
        <sponsorshipWithdrawnDate />
        <sponsorshipDate>2015-04-29</sponsorshipDate>
        <identifiers>
          <lisID>791</lisID>
          <gpoId>8239</gpoId>
          <bioguideId>M000639</bioguideId>
        </identifiers>
        <isOriginalCosponsor>False</isOriginalCosponsor>
        <state>NJ</state>
      </item>
    </cosponsors>
    <notes />
    <laws />
    <latestAction>
      <actionDate>2015-03-12</actionDate>
      <text>Read twice and referred to the Committee on Banking, Housing, and Urban Affairs.</text>
      <links />
    </latestAction>
    <title>Permanently Protecting Tenants at Foreclosure Act of 2015</title>
    <summaries>
      <billSummaries>
        <item>
          <versionCode>00</versionCode>
          <actionDesc>Introduced in Senate</actionDesc>
          <text><![CDATA[<p><b>Permanently Protecting Tenants at Foreclosure Act of 2015</b></p> <p>This bill amends the Protecting Tenants at Foreclosure Act of 2009 to repeal its sunset date December 31, 2014 (thus making the Act permanent). </p> <p>This bill restores and revives such Act, the provisions of law amended or repealed by it, and any regulations promulgated pursuant to it, as were in effect on December 31, 2014, as if the sunset had not taken effect.</p>]]></text>
          <lastSummaryUpdateDate>2015-04-22T20:15:38Z</lastSummaryUpdateDate>
          <updateDate>2015-03-12T04:00:00Z</updateDate>
          <actionDate>2015-03-12</actionDate>
          <name>Introduced in Senate</name>
        </item>
      </billSummaries>
    </summaries>
    <relatedBills>
      <item>
        <type>HR</type>
        <latestTitle>Permanently Protecting Tenants at Foreclosure Act of 2015</latestTitle>
        <latestAction>
          <actionDate>2015-03-13</actionDate>
          <text>Referred to the House Committee on Financial Services.</text>
        </latestAction>
        <number>1354</number>
        <congress>114</congress>
        <relationshipDetails>
          <item>
            <type>Identical bill</type>
            <identifiedBy>CRS</identifiedBy>
          </item>
        </relationshipDetails>
      </item>
    </relatedBills>
    <congress>114</congress>
    <version>1.0.0</version>
    <committees>
      <billCommittees>
        <item>
          <name>Banking, Housing, and Urban Affairs Committee</name>
          <chamber>Senate</chamber>
          <activities>
            <item>
              <name>Referred to</name>
              <date>2015-03-12T19:24:35Z</date>
            </item>
          </activities>
          <type>Standing</type>
          <subcommittees />
          <systemCode>ssbk00</systemCode>
        </item>
      </billCommittees>
    </committees>
    <originChamber>Senate</originChamber>
    <committeeReports />
    <subjects>
      <billSubjects>
        <policyArea>
          <name>Housing and Community Development</name>
        </policyArea>
        <legislativeSubjects>
          <item>
            <name>Housing finance and home ownership</name>
          </item>
          <item>
            <name>Low- and moderate-income housing</name>
          </item>
        </legislativeSubjects>
      </billSubjects>
    </subjects>
    <actions>
      <actionTypeCounts>
        <referredToCommittee>1</referredToCommittee>
        <introducedInSenate>1</introducedInSenate>
      </actionTypeCounts>
      <actionByCounts>
        <senate>2</senate>
      </actionByCounts>
      <item>
        <actionDate>2015-03-12</actionDate>
        <committee>
          <name>Banking, Housing, and Urban Affairs Committee</name>
          <systemCode>ssbk00</systemCode>
        </committee>
        <links />
        <sourceSystem>
          <code>0</code>
          <name>Senate</name>
        </sourceSystem>
        <text>Read twice and referred to the Committee on Banking, Housing, and Urban Affairs.</text>
        <type>IntroReferral</type>
      </item>
      <item>
        <actionDate>2015-03-12</actionDate>
        <links />
        <actionCode>10000</actionCode>
        <type>IntroReferral</type>
        <text>Introduced in Senate</text>
        <committee />
        <sourceSystem>
          <code>9</code>
          <name>Library of Congress</name>
        </sourceSystem>
      </item>
    </actions>
    <sponsors>
      <item>
        <firstName>Richard</firstName>
        <bioguideId>B001277</bioguideId>
        <byRequestType />
        <identifiers>
          <bioguideId>B001277</bioguideId>
          <gpoId>8332</gpoId>
          <lisID>2076</lisID>
        </identifiers>
        <fullName>Sen. Blumenthal, Richard [D-CT]</fullName>
        <lastName>Blumenthal</lastName>
        <party>D</party>
        <middleName />
        <state>CT</state>
      </item>
    </sponsors>
    <policyArea>
      <name>Housing and Community Development</name>
    </policyArea>
    <billNumber>730</billNumber>
    <recordedVotes />
    <cboCostEstimates />
    <billType>S</billType>
    <titles>
      <item>
        <title>Permanently Protecting Tenants at Foreclosure Act of 2015</title>
        <parentTitleType />
        <titleType>Short Titles as Introduced</titleType>
        <chamberName />
        <chamberCode />
      </item>
      <item>
        <title>A bill to permanently extend the Protecting Tenants at Foreclosure Act of 2009.</title>
        <parentTitleType />
        <titleType>Official Title as Introduced</titleType>
        <chamberName />
        <chamberCode />
      </item>
      <item>
        <title>Permanently Protecting Tenants at Foreclosure Act of 2015</title>
        <parentTitleType />
        <titleType>Display Title</titleType>
        <chamberName />
        <chamberCode />
      </item>
    </titles>
    <createDate>2015-03-13T05:51:11Z</createDate>
    <amendments />
  </bill>
  <dublinCore xmlns:dc="http://purl.org/dc/elements/1.1/">
    <dc:format>text/xml</dc:format>
    <dc:language>EN</dc:language>
    <dc:rights>Pursuant to Title 17 Section 105 of the United States Code, this file is not subject to copyright protection and is in the public domain.</dc:rights>
    <dc:contributor>Congressional Research Service, Library of Congress</dc:contributor>
    <dc:description>This file contains bill summaries and statuses for federal legislation. A bill summary describes the most significant provisions of a piece of legislation and details the effects the legislative text may have on current law and federal programs. Bill summaries are authored by the Congressional Research Service (CRS) of the Library of Congress. As stated in Public Law 91-510 (2 USC 166 (d)(6)), one of the duties of CRS is "to prepare summaries and digests of bills and resolutions of a public general nature introduced in the Senate or House of Representatives". For more information, refer to the User Guide that accompanies this file.</dc:description>
  </dublinCore>
</billStatus>

