<?xml version="1.0" encoding="UTF-8"?>
<billStatus>
  <bill>
    <title>End Trafficking of the Terminated Unborn Act of 2015</title>
    <updateDate>2017-10-27T18:02:53Z</updateDate>
    <originChamber>House</originChamber>
    <actions>
      <item>
        <actionDate>2015-07-31</actionDate>
        <committee>
          <systemCode>hsif14</systemCode>
          <name>Health Subcommittee</name>
        </committee>
        <links />
        <sourceSystem>
          <code>1</code>
          <name>House committee actions</name>
        </sourceSystem>
        <text>Referred to the Subcommittee on Health.</text>
        <type>Committee</type>
      </item>
      <item>
        <actionDate>2015-07-27</actionDate>
        <committee>
          <systemCode>hsif00</systemCode>
          <name>Energy and Commerce Committee</name>
        </committee>
        <sourceSystem>
          <code>2</code>
          <name>House floor actions</name>
        </sourceSystem>
        <text>Referred to the House Committee on Energy and Commerce.</text>
        <links />
        <type>IntroReferral</type>
        <actionCode>H11100</actionCode>
      </item>
      <item>
        <actionDate>2015-07-27</actionDate>
        <committee />
        <sourceSystem>
          <code>9</code>
          <name>Library of Congress</name>
        </sourceSystem>
        <text>Introduced in House</text>
        <links />
        <type>IntroReferral</type>
        <actionCode>Intro-H</actionCode>
      </item>
      <item>
        <actionDate>2015-07-27</actionDate>
        <committee />
        <sourceSystem>
          <code>9</code>
          <name>Library of Congress</name>
        </sourceSystem>
        <text>Introduced in House</text>
        <links />
        <type>IntroReferral</type>
        <actionCode>1000</actionCode>
      </item>
      <actionTypeCounts>
        <billReferrals>1</billReferrals>
        <introducedInHouse>1</introducedInHouse>
        <placeholderTextForH>1</placeholderTextForH>
        <introducedInTheHouse>1</introducedInTheHouse>
      </actionTypeCounts>
      <actionByCounts>
        <houseOfRepresentatives>4</houseOfRepresentatives>
      </actionByCounts>
    </actions>
    <recordedVotes />
    <relatedBills />
    <cboCostEstimates />
    <createDate>2015-07-28T14:38:35Z</createDate>
    <sponsors>
      <item>
        <bioguideId>L000564</bioguideId>
        <fullName>Rep. Lamborn, Doug [R-CO-5]</fullName>
        <middleName />
        <identifiers>
          <lisID>1834</lisID>
          <bioguideId>L000564</bioguideId>
          <gpoId>7863</gpoId>
        </identifiers>
        <state>CO</state>
        <firstName>Doug</firstName>
        <lastName>Lamborn</lastName>
        <byRequestType />
        <party>R</party>
        <district>5</district>
      </item>
    </sponsors>
    <congress>114</congress>
    <notes />
    <amendments />
    <calendarNumbers />
    <subjects>
      <billSubjects>
        <policyArea>
          <name>Health</name>
        </policyArea>
        <legislativeSubjects>
          <item>
            <name>Abortion</name>
          </item>
          <item>
            <name>Department of Health and Human Services</name>
          </item>
          <item>
            <name>Medical research</name>
          </item>
          <item>
            <name>National Institutes of Health (NIH)</name>
          </item>
          <item>
            <name>Organ and tissue donation and transplantation</name>
          </item>
          <item>
            <name>Research administration and funding</name>
          </item>
        </legislativeSubjects>
      </billSubjects>
    </subjects>
    <summaries>
      <billSummaries>
        <item>
          <name>Introduced in House</name>
          <updateDate>2015-07-27T04:00:00Z</updateDate>
          <versionCode>00</versionCode>
          <actionDesc>Introduced in House</actionDesc>
          <actionDate>2015-07-27</actionDate>
          <text><![CDATA[<p><b>End Trafficking of the Terminated Unborn Act of 2015</b></p> <p>This bill amends the Public Health Service Act to prohibit the use of tissue from an induced abortion for research conducted or supported by the National Institutes of Health on the transplantation of fetal tissue for therapeutic purposes.</p> Soliciting or acquiring a donation of fetal tissue from an induced abortion for a purpose other than disposal is prohibited.]]></text>
          <lastSummaryUpdateDate>2015-11-16T20:23:49Z</lastSummaryUpdateDate>
        </item>
      </billSummaries>
    </summaries>
    <committeeReports />
    <version>1.0.0</version>
    <latestAction>
      <text>Referred to the Subcommittee on Health.</text>
      <links />
      <actionDate>2015-07-31</actionDate>
    </latestAction>
    <introducedDate>2015-07-27</introducedDate>
    <constitutionalAuthorityStatementText><![CDATA[<pre>From the Congressional Record Online through the Government Publishing Office [<a href='http://www.gpo.gov'>www.gpo.gov</a>]By Mr. LAMBORN:H.R. 3215.Congress has the power to enact this legislation pursuantto the following:Clause 3 of Section 8 of Article 1 of the Constitutionstates that Congress has the authority to ``regulate Commercewith foreign nations, and among the several states.''[Page H5523]</pre>]]></constitutionalAuthorityStatementText>
    <titles>
      <item>
        <chamberCode />
        <chamberName />
        <parentTitleType />
        <titleType>Short Titles as Introduced</titleType>
        <title>End Trafficking of the Terminated Unborn Act of 2015</title>
      </item>
      <item>
        <chamberCode />
        <chamberName />
        <parentTitleType />
        <titleType>Official Title as Introduced</titleType>
        <title>To prohibit any person from soliciting or knowingly acquiring, receiving, or accepting a donation of human fetal tissue for any purpose other than disposal of the tissue if the donation affects interstate commerce and the tissue will be or is obtained pursuant to an induced abortion.</title>
      </item>
      <item>
        <chamberCode />
        <chamberName />
        <parentTitleType />
        <titleType>Display Title</titleType>
        <title>End Trafficking of the Terminated Unborn Act of 2015</title>
      </item>
    </titles>
    <committees>
      <billCommittees>
        <item>
          <type>Standing</type>
          <name>Energy and Commerce Committee</name>
          <chamber>House</chamber>
          <systemCode>hsif00</systemCode>
          <subcommittees>
            <item>
              <systemCode>hsif14</systemCode>
              <name>Health Subcommittee</name>
              <activities>
                <item>
                  <name>Referred to</name>
                  <date>2015-07-31T20:47:36Z</date>
                </item>
              </activities>
            </item>
          </subcommittees>
          <activities>
            <item>
              <name>Referred to</name>
              <date>2015-07-27T16:02:40Z</date>
            </item>
          </activities>
        </item>
      </billCommittees>
    </committees>
    <billType>HR</billType>
    <billNumber>3215</billNumber>
    <laws />
    <cosponsors>
      <item>
        <party>R</party>
        <fullName>Rep. Pitts, Joseph R. [R-PA-16]</fullName>
        <state>PA</state>
        <sponsorshipWithdrawnDate />
        <lastName>PITTS</lastName>
        <identifiers>
          <gpoId>8134</gpoId>
          <lisID>1514</lisID>
          <bioguideId>P000373</bioguideId>
        </identifiers>
        <firstName>JOSEPH</firstName>
        <isOriginalCosponsor>False</isOriginalCosponsor>
        <district>16</district>
        <middleName>R.</middleName>
        <sponsorshipDate>2015-07-29</sponsorshipDate>
        <bioguideId>P000373</bioguideId>
      </item>
      <item>
        <party>R</party>
        <fullName>Rep. Harris, Andy [R-MD-1]</fullName>
        <state>MD</state>
        <sponsorshipWithdrawnDate />
        <lastName>Harris</lastName>
        <identifiers>
          <gpoId>7976</gpoId>
          <lisID>2026</lisID>
          <bioguideId>H001052</bioguideId>
        </identifiers>
        <firstName>Andy</firstName>
        <isOriginalCosponsor>False</isOriginalCosponsor>
        <district>1</district>
        <middleName />
        <sponsorshipDate>2015-07-29</sponsorshipDate>
        <bioguideId>H001052</bioguideId>
      </item>
      <item>
        <party>R</party>
        <fullName>Rep. Gowdy, Trey [R-SC-4]</fullName>
        <state>SC</state>
        <sponsorshipWithdrawnDate />
        <lastName>Gowdy</lastName>
        <identifiers>
          <bioguideId>G000566</bioguideId>
          <gpoId>8144</gpoId>
          <lisID>2058</lisID>
        </identifiers>
        <firstName>Trey</firstName>
        <isOriginalCosponsor>False</isOriginalCosponsor>
        <district>4</district>
        <middleName />
        <sponsorshipDate>2015-07-29</sponsorshipDate>
        <bioguideId>G000566</bioguideId>
      </item>
      <item>
        <party>R</party>
        <fullName>Rep. Walberg, Tim [R-MI-7]</fullName>
        <state>MI</state>
        <sponsorshipWithdrawnDate />
        <lastName>Walberg</lastName>
        <identifiers>
          <lisID>1855</lisID>
          <bioguideId>W000798</bioguideId>
          <gpoId>7992</gpoId>
        </identifiers>
        <firstName>Tim</firstName>
        <isOriginalCosponsor>False</isOriginalCosponsor>
        <district>7</district>
        <middleName />
        <sponsorshipDate>2015-07-29</sponsorshipDate>
        <bioguideId>W000798</bioguideId>
      </item>
      <item>
        <party>R</party>
        <fullName>Rep. Johnson, Sam [R-TX-3]</fullName>
        <state>TX</state>
        <sponsorshipWithdrawnDate />
        <lastName>JOHNSON</lastName>
        <identifiers>
          <bioguideId>J000174</bioguideId>
          <gpoId>8159</gpoId>
          <lisID>603</lisID>
        </identifiers>
        <firstName>SAM</firstName>
        <isOriginalCosponsor>False</isOriginalCosponsor>
        <district>3</district>
        <middleName />
        <sponsorshipDate>2015-07-29</sponsorshipDate>
        <bioguideId>J000174</bioguideId>
      </item>
      <item>
        <party>R</party>
        <fullName>Rep. Mooney, Alexander X. [R-WV-2]</fullName>
        <state>WV</state>
        <sponsorshipWithdrawnDate />
        <lastName>Mooney</lastName>
        <identifiers>
          <bioguideId>M001195</bioguideId>
          <gpoId />
          <lisID>2277</lisID>
        </identifiers>
        <firstName>Alexander</firstName>
        <isOriginalCosponsor>False</isOriginalCosponsor>
        <district>2</district>
        <middleName>X.</middleName>
        <sponsorshipDate>2015-07-29</sponsorshipDate>
        <bioguideId>M001195</bioguideId>
      </item>
      <item>
        <party>R</party>
        <fullName>Rep. Stewart, Chris [R-UT-2]</fullName>
        <state>UT</state>
        <sponsorshipWithdrawnDate />
        <lastName>Stewart</lastName>
        <identifiers>
          <lisID>2168</lisID>
          <gpoId />
          <bioguideId>S001192</bioguideId>
        </identifiers>
        <firstName>Chris</firstName>
        <isOriginalCosponsor>False</isOriginalCosponsor>
        <district>2</district>
        <middleName />
        <sponsorshipDate>2015-07-29</sponsorshipDate>
        <bioguideId>S001192</bioguideId>
      </item>
      <item>
        <party>R</party>
        <fullName>Rep. Wenstrup, Brad R. [R-OH-2]</fullName>
        <state>OH</state>
        <sponsorshipWithdrawnDate />
        <lastName>Wenstrup</lastName>
        <identifiers>
          <lisID>2152</lisID>
          <bioguideId>W000815</bioguideId>
          <gpoId />
        </identifiers>
        <firstName>Brad</firstName>
        <isOriginalCosponsor>False</isOriginalCosponsor>
        <district>2</district>
        <middleName>R.</middleName>
        <sponsorshipDate>2015-07-29</sponsorshipDate>
        <bioguideId>W000815</bioguideId>
      </item>
      <item>
        <party>R</party>
        <fullName>Rep. Jones, Walter B., Jr. [R-NC-3]</fullName>
        <state>NC</state>
        <sponsorshipWithdrawnDate />
        <lastName>JONES</lastName>
        <identifiers>
          <lisID>612</lisID>
          <gpoId>8026</gpoId>
          <bioguideId>J000255</bioguideId>
        </identifiers>
        <firstName>WALTER</firstName>
        <isOriginalCosponsor>False</isOriginalCosponsor>
        <district>3</district>
        <middleName>B.</middleName>
        <sponsorshipDate>2015-07-29</sponsorshipDate>
        <bioguideId>J000255</bioguideId>
      </item>
      <item>
        <party>R</party>
        <fullName>Rep. Chabot, Steve [R-OH-1]</fullName>
        <state>OH</state>
        <sponsorshipWithdrawnDate />
        <lastName>CHABOT</lastName>
        <identifiers>
          <lisID>186</lisID>
          <bioguideId>C000266</bioguideId>
          <gpoId>8091</gpoId>
        </identifiers>
        <firstName>STEVE</firstName>
        <isOriginalCosponsor>False</isOriginalCosponsor>
        <district>1</district>
        <middleName />
        <sponsorshipDate>2015-07-29</sponsorshipDate>
        <bioguideId>C000266</bioguideId>
      </item>
      <item>
        <party>R</party>
        <fullName>Rep. Babin, Brian [R-TX-36]</fullName>
        <state>TX</state>
        <sponsorshipWithdrawnDate />
        <lastName>Babin</lastName>
        <identifiers>
          <lisID>2270</lisID>
          <gpoId />
          <bioguideId>B001291</bioguideId>
        </identifiers>
        <firstName>Brian</firstName>
        <isOriginalCosponsor>False</isOriginalCosponsor>
        <district>36</district>
        <middleName />
        <sponsorshipDate>2015-09-11</sponsorshipDate>
        <bioguideId>B001291</bioguideId>
      </item>
      <item>
        <party>R</party>
        <fullName>Rep. Conaway, K. Michael [R-TX-11]</fullName>
        <state>TX</state>
        <sponsorshipWithdrawnDate />
        <lastName>Conaway</lastName>
        <identifiers>
          <gpoId>8167</gpoId>
          <lisID>1805</lisID>
          <bioguideId>C001062</bioguideId>
        </identifiers>
        <firstName>K.</firstName>
        <isOriginalCosponsor>False</isOriginalCosponsor>
        <district>11</district>
        <middleName>Michael</middleName>
        <sponsorshipDate>2015-09-11</sponsorshipDate>
        <bioguideId>C001062</bioguideId>
      </item>
      <item>
        <party>R</party>
        <fullName>Rep. Pearce, Stevan [R-NM-2]</fullName>
        <state>NM</state>
        <sponsorshipWithdrawnDate />
        <lastName>Pearce</lastName>
        <identifiers>
          <lisID>1738</lisID>
          <bioguideId>P000588</bioguideId>
          <gpoId>8057</gpoId>
        </identifiers>
        <firstName>Stevan</firstName>
        <isOriginalCosponsor>False</isOriginalCosponsor>
        <district>2</district>
        <middleName />
        <sponsorshipDate>2015-09-11</sponsorshipDate>
        <bioguideId>P000588</bioguideId>
      </item>
      <item>
        <party>R</party>
        <fullName>Rep. Carter, Earl L. "Buddy" [R-GA-1]</fullName>
        <state>GA</state>
        <sponsorshipWithdrawnDate />
        <lastName>Carter</lastName>
        <identifiers>
          <lisID>2236</lisID>
          <bioguideId>C001103</bioguideId>
          <gpoId />
        </identifiers>
        <firstName>Earl</firstName>
        <isOriginalCosponsor>False</isOriginalCosponsor>
        <district>1</district>
        <middleName>L. "Buddy"</middleName>
        <sponsorshipDate>2015-09-11</sponsorshipDate>
        <bioguideId>C001103</bioguideId>
      </item>
      <item>
        <party>R</party>
        <fullName>Rep. Hartzler, Vicky [R-MO-4]</fullName>
        <state>MO</state>
        <sponsorshipWithdrawnDate />
        <lastName>Hartzler</lastName>
        <identifiers>
          <lisID>2032</lisID>
          <bioguideId>H001053</bioguideId>
          <gpoId>8012</gpoId>
        </identifiers>
        <firstName>Vicky</firstName>
        <isOriginalCosponsor>False</isOriginalCosponsor>
        <district>4</district>
        <middleName />
        <sponsorshipDate>2015-09-18</sponsorshipDate>
        <bioguideId>H001053</bioguideId>
      </item>
      <item>
        <party>R</party>
        <fullName>Rep. Rouzer, David [R-NC-7]</fullName>
        <state>NC</state>
        <sponsorshipWithdrawnDate />
        <lastName>Rouzer</lastName>
        <identifiers>
          <bioguideId>R000603</bioguideId>
          <gpoId />
          <lisID>2256</lisID>
        </identifiers>
        <firstName>David</firstName>
        <isOriginalCosponsor>False</isOriginalCosponsor>
        <district>7</district>
        <middleName />
        <sponsorshipDate>2015-09-18</sponsorshipDate>
        <bioguideId>R000603</bioguideId>
      </item>
    </cosponsors>
    <policyArea>
      <name>Health</name>
    </policyArea>
  </bill>
  <dublinCore xmlns:dc="http://purl.org/dc/elements/1.1/">
    <dc:format>text/xml</dc:format>
    <dc:language>EN</dc:language>
    <dc:rights>Pursuant to Title 17 Section 105 of the United States Code, this file is not subject to copyright protection and is in the public domain.</dc:rights>
    <dc:contributor>Congressional Research Service, Library of Congress</dc:contributor>
    <dc:description>This file contains bill summaries and statuses for federal legislation. A bill summary describes the most significant provisions of a piece of legislation and details the effects the legislative text may have on current law and federal programs. Bill summaries are authored by the Congressional Research Service (CRS) of the Library of Congress. As stated in Public Law 91-510 (2 USC 166 (d)(6)), one of the duties of CRS is "to prepare summaries and digests of bills and resolutions of a public general nature introduced in the Senate or House of Representatives". For more information, refer to the User Guide that accompanies this file.</dc:description>
  </dublinCore>
</billStatus>

